examples/__init__.py
examples/typer.py
promptforge/__init__.py
promptforge/customization.py
promptforge/factory.py
promptforge/pipeline.py
promptforge/prompts/__init__.py
promptforge/prompts/base.py
promptforge/prompts/cascading_select.py
promptforge/prompts/confirm.py
promptforge/prompts/multiselect.py
promptforge/prompts/select.py
promptforge/prompts/text_input.py
promptforge/renderers/__init__.py
promptforge/renderers/base.py
promptforge/renderers/cascading_select.py
promptforge/renderers/confirm.py
promptforge/renderers/multiselect.py
promptforge/renderers/select.py
promptforge/renderers/text_input.py
promptforge/utils/__init__.py
promptforge/utils/cancel.py
promptforge/utils/event_emitter.py
promptforge/utils/exceptions.py
promptforge/utils/symbols.py
promptforge/utils/themes.py
promptforge/utils/validators.py
tests/__init__.py
tests/test_promptforge.py
promptforge-0.1.0.dist-info/LICENSE
promptforge-0.1.0.dist-info/METADATA
promptforge-0.1.0.dist-info/WHEEL
promptforge-0.1.0.dist-info/top_level.txt
promptforge-0.1.0.dist-info/RECORD
