Metadata-Version: 2.1
Name: promptforge
Version: 0.1.0
Home-page: https://github.com/victor-mariano-leite/promptforge
Author: Victor Mariano Leite
Author-email: marianoleite44@gmail.com
License-File: LICENSE
Requires-Dist: rich >=12
Requires-Dist: requests
Requires-Dist: prompt-toolkit
